robustredirects/__init__.py
robustredirects/admin.py
robustredirects/apps.py
robustredirects/dynamic_urls.py
robustredirects/middleware.py
robustredirects/models.py
robustredirects/tests.py
robustredirects/urls.py
robustredirects/utils.py
robustredirects/views.py
robustredirects/locale/en/LC_MESSAGES/django.po
robustredirects/locale/ru/LC_MESSAGES/django.mo
robustredirects/locale/ru/LC_MESSAGES/django.po
robustredirects/locale/uk/LC_MESSAGES/django.mo
robustredirects/locale/uk/LC_MESSAGES/django.po
robustredirects/management/__init__.py
robustredirects/management/commands/__init__.py
robustredirects/management/commands/convert_redirects.py
robustredirects/templates/change_form.html
django_robust_redirects-1.1.2.dist-info/LICENSE
django_robust_redirects-1.1.2.dist-info/METADATA
django_robust_redirects-1.1.2.dist-info/WHEEL
django_robust_redirects-1.1.2.dist-info/top_level.txt
django_robust_redirects-1.1.2.dist-info/RECORD
