Metadata-Version: 2.1
Name: django-robust-redirects
Version: 1.1.2
Summary: A more robust and feature full django redirect package
Home-page: http://github.com/spothero/django-robust-redirects
Download-URL: http://github.com/spothero/django-robust-redirects/tarball/0.10.0
Author: SpotHero
Author-email: pypi@spothero.com
Classifier: Development Status :: 4 - Beta
Classifier: Framework :: Django
Classifier: Intended Audience :: Developers
Classifier: License :: OSI Approved :: Apache Software License
Classifier: Operating System :: OS Independent
Classifier: Programming Language :: Python
Requires-Python: >=3.6
License-File: LICENSE
Requires-Dist: django (>=3.2)
Requires-Dist: six (<2,>=1.12.0)
